{
  "modified": "Tue Feb 26 2019 18:11:57 GMT+0800 (中国标准时间)",
  "background": "rgb(124,145,155)",
  "width": 200,
  "height": 200,
  "comps": [
    {
      "type": "shape",
      "background": "rgb(255,255,255)",
      "pixelPerfect": true,
      "points": [
        100,
        141.48,
        98.2,
        141.48,
        96.5,
        140.78,
        95.22,
        139.5,
        60.78,
        105.06,
        60.76,
        105.04,
        59.32,
        103.76,
        58.5,
        101.92,
        58.5,
        100,
        58.5,
        99.8,
        58.5,
        99.58,
        58.5,
        99.52,
        58.5,
        99.46,
        58.52,
        99.38,
        58.52,
        99.32,
        58.54,
        99.26,
        58.54,
        99.2,
        58.54,
        99.12,
        58.56,
        99.06,
        58.56,
        98.98,
        58.58,
        98.9,
        58.8,
        97.48,
        59.46,
        96.22,
        60.48,
        95.2,
        60.74,
        94.94,
        60.78,
        94.92,
        95.2,
        60.5,
        96.48,
        59.22,
        98.18,
        58.52,
        99.98,
        58.52,
        101.78,
        58.52,
        103.48,
        59.22,
        104.76,
        60.5,
        106.04,
        61.78,
        106.74,
        63.48,
        106.74,
        65.28,
        106.74,
        67.08,
        106.04,
        68.78,
        104.76,
        70.06,
        81.6,
        93.24,
        134.72,
        93.24,
        138.46,
        93.24,
        141.48,
        96.28,
        141.48,
        100,
        141.48,
        103.74,
        138.44,
        106.76,
        134.72,
        106.76,
        81.62,
        106.76,
        104.78,
        129.9,
        106.06,
        131.18,
        106.76,
        132.88,
        106.76,
        134.68,
        106.76,
        136.48,
        106.06,
        138.18,
        104.78,
        139.46,
        103.5,
        140.78,
        101.8,
        141.48,
        100,
        141.48
      ],
      "segments": [
        1,
        4,
        2,
        2,
        4,
        2,
        2,
        4,
        4,
        4,
        2,
        4,
        2,
        2,
        2,
        4,
        4,
        4,
        4,
        2,
        2,
        4,
        4,
        2,
        2,
        4,
        4,
        4,
        5
      ]
    },
    {
      "type": "shape",
      "background": "rgb(255,255,255)",
      "pixelPerfect": true,
      "opacity": 0.7,
      "points": [
        100.78,
        180,
        89.98,
        180,
        79.5,
        177.88,
        69.64,
        173.72,
        60.12,
        169.7,
        51.56,
        163.92,
        44.22,
        156.58,
        36.88,
        149.24,
        31.1,
        140.68,
        27.08,
        131.16,
        22.88,
        121.28,
        20.78,
        110.8,
        20.78,
        100,
        20.78,
        89.2,
        22.9,
        78.72,
        27.06,
        68.86,
        31.08,
        59.34,
        36.86,
        50.78,
        44.2,
        43.44,
        51.54,
        36.1,
        60.1,
        30.32,
        69.62,
        26.3,
        79.48,
        22.12,
        89.96,
        20.02,
        100.76,
        20.02,
        111.56,
        20.02,
        122.04,
        22.14,
        131.9,
        26.3,
        141.42,
        30.32,
        149.98,
        36.1,
        157.32,
        43.44,
        164.66,
        50.78,
        170.44,
        59.34,
        174.46,
        68.86,
        176.46,
        73.6,
        178.02,
        78.56,
        179.06,
        83.56,
        179.48,
        85.54,
        178.98,
        87.56,
        177.7,
        89.14,
        176.42,
        90.72,
        174.5,
        91.64,
        172.46,
        91.64,
        172.36,
        91.64,
        169.2,
        91.64,
        166.42,
        89.38,
        165.76,
        86.24,
        159.3,
        55.7,
        131.96,
        33.54,
        100.74,
        33.54,
        82.92,
        33.54,
        66.16,
        40.52,
        53.58,
        53.22,
        41,
        65.9,
        34.14,
        82.7,
        34.28,
        100.54,
        34.56,
        136.9,
        64.38,
        166.48,
        100.74,
        166.48,
        131.98,
        166.48,
        159.32,
        144.3,
        165.78,
        113.74,
        166.44,
        110.64,
        169.22,
        108.4,
        172.4,
        108.4,
        174.46,
        108.4,
        176.38,
        109.32,
        177.68,
        110.92,
        178.96,
        112.5,
        179.46,
        114.54,
        179.04,
        116.54,
        178,
        121.52,
        176.46,
        126.44,
        174.46,
        131.16,
        170.44,
        140.68,
        164.66,
        149.24,
        157.32,
        156.58,
        149.98,
        163.92,
        141.42,
        169.7,
        131.9,
        173.72,
        122.04,
        177.88,
        111.58,
        180,
        100.78,
        180
      ],
      "segments": [
        1,
        4,
        4,
        4,
        4,
        4,
        4,
        4,
        4,
        4,
        4,
        4,
        4,
        4,
        4,
        2,
        4,
        4,
        4,
        4,
        4,
        4,
        4,
        4,
        4,
        4,
        4,
        4,
        4,
        5
      ]
    }
  ]
}